csv2sql/__init__.py
csv2sql/cli.py
csv2sql/converter.py
csv2sql_wangchenbu-0.1.0.dist-info/LICENSE
csv2sql_wangchenbu-0.1.0.dist-info/METADATA
csv2sql_wangchenbu-0.1.0.dist-info/WHEEL
csv2sql_wangchenbu-0.1.0.dist-info/entry_points.txt
csv2sql_wangchenbu-0.1.0.dist-info/top_level.txt
csv2sql_wangchenbu-0.1.0.dist-info/RECORD
