Metadata-Version: 2.1
Name: csv2sql-wangchenbu
Version: 0.1.0
Summary: Convert CSV files to SQL create table and insert statements
Home-page: https://github.com/wangchenbu/csv2sql
Author: wangchenbu
Author-email: 3206590839@qq.com
Project-URL: Bug Reports, https://github.com/yourusername/csv2sql/issues
Project-URL: Source, https://github.com/yourusername/csv2sql
Project-URL: Documentation, https://github.com/yourusername/csv2sql#readme
Keywords: csv,sql,database,conversion,etl
Classifier: Development Status :: 4 - Beta
Classifier: Intended Audience :: Developers
Classifier: License :: OSI Approved :: MIT License
Classifier: Operating System :: OS Independent
Classifier: Programming Language :: Python :: 3
Classifier: Programming Language :: Python :: 3.6
Classifier: Programming Language :: Python :: 3.7
Classifier: Programming Language :: Python :: 3.8
Classifier: Programming Language :: Python :: 3.9
Classifier: Programming Language :: Python :: 3.10
Classifier: Programming Language :: Python :: 3.11
Classifier: Topic :: Database
Classifier: Topic :: Software Development :: Libraries :: Python Modules
Requires-Python: >=3.6
License-File: LICENSE
Requires-Dist: pandas
Requires-Dist: sqlalchemy
Requires-Dist: click
Provides-Extra: mssql
Requires-Dist: pyodbc ; extra == 'mssql'
Provides-Extra: mysql
Requires-Dist: mysqlclient ; extra == 'mysql'
Provides-Extra: oracle
Requires-Dist: cx-Oracle ; extra == 'oracle'
Provides-Extra: postgresql
Requires-Dist: psycopg2-binary ; extra == 'postgresql'
Provides-Extra: sqlite
